jcgutier_logger/__init__.py
jcgutier_logger/logger.py
jcgutier_logger/settings.py
jcgutier_logger-0.1.1.dist-info/METADATA
jcgutier_logger-0.1.1.dist-info/WHEEL
jcgutier_logger-0.1.1.dist-info/RECORD
